django_mysql_geventpool_27/__init__.py
django_mysql_geventpool_27/utils.py
django_mysql_geventpool_27/backends/__init__.py
django_mysql_geventpool_27/backends/connection_pool.py
django_mysql_geventpool_27/backends/mysql/__init__.py
django_mysql_geventpool_27/backends/mysql/base.py
django_mysql_geventpool_27/backends/mysql/connection_pool.py
django_mysql_geventpool_27/backends/mysql/creation.py
django_mysql_geventpool_27/backends/mysql_gis/__init__.py
django_mysql_geventpool_27/backends/mysql_gis/base.py
django_mysql_geventpool_27-0.3.1.dist-info/LICENSE
django_mysql_geventpool_27-0.3.1.dist-info/METADATA
django_mysql_geventpool_27-0.3.1.dist-info/WHEEL
django_mysql_geventpool_27-0.3.1.dist-info/top_level.txt
django_mysql_geventpool_27-0.3.1.dist-info/RECORD
