Metadata-Version: 2.1
Name: django-mysql-geventpool-27
Version: 0.3.1
Summary: Add a MySQL connection pool for django using gevent
Home-page: UNKNOWN
Author: lollo789
Author-email: laurent@labatut.net
License: Apache 2.0
Platform: UNKNOWN
Requires-Dist: django (<2.0)
Requires-Dist: gevent
